DynamicAxisControl/DynamicAxisControl.py
DynamicAxisControl/__init__.py
DynamicAxisControl-1.0.2.dist-info/LICENSE
DynamicAxisControl-1.0.2.dist-info/METADATA
DynamicAxisControl-1.0.2.dist-info/WHEEL
DynamicAxisControl-1.0.2.dist-info/entry_points.txt
DynamicAxisControl-1.0.2.dist-info/top_level.txt
DynamicAxisControl-1.0.2.dist-info/RECORD
