Metadata-Version: 2.1
Name: DynamicAxisControl
Version: 1.0.2
Summary: Linear trajectory generator for robotic axes, with the ability to synchronize up to two speed profiles
Author: Davide Zuanon
Author-email: d.zuanon87@gmail.com
License: unlicense
Classifier: Development Status :: 4 - Beta
Classifier: Intended Audience :: Science/Research
Classifier: License :: OSI Approved :: The Unlicense (Unlicense)
Classifier: Operating System :: POSIX :: Linux
Classifier: Programming Language :: Python :: 3.7
Classifier: Programming Language :: Python :: 3.10
License-File: LICENSE
Requires-Dist: matplotlib
Requires-Dist: numpy
Requires-Dist: scipy
